scribe_store/__init__.py
scribe_store/admin.py
scribe_store/apps.py
scribe_store/models.py
scribe_store/management/__init__.py
scribe_store/management/commands/__init__.py
scribe_store/management/commands/scribe.py
scribe_store/management/commands/scribe_new.py
scribe_store/migrations/0001_initial.py
scribe_store/migrations/__init__.py
django_scribe_store-0.1.0.dist-info/LICENSE
django_scribe_store-0.1.0.dist-info/WHEEL
django_scribe_store-0.1.0.dist-info/METADATA
django_scribe_store-0.1.0.dist-info/RECORD
